{"seed":161137312,"allCommands":[[{"command":"m u_1 s","agentID":0},{"command":"m u_2 s","agentID":1}],[{"command":"m u_1 c","agentID":0},{"command":"m u_2 c","agentID":1}],[{"command":"m u_1 n","agentID":0},{"command":"m u_2 n","agentID":1}],[],[{"command":"m u_1 s","agentID":0},{"command":"m u_2 s","agentID":1}],[{"command":"m u_1 c","agentID":0},{"command":"m u_2 c","agentID":1}],[{"command":"m u_1 n","agentID":0},{"command":"m u_2 n","agentID":1}],[],[{"command":"m u_1 s","agentID":0},{"command":"m u_2 s","agentID":1}],[{"command":"m u_1 c","agentID":0},{"command":"m u_2 c","agentID":1}],[{"command":"m u_1 n","agentID":0},{"command":"m u_2 n","agentID":1}],[],[{"command":"m u_1 s","agentID":0},{"command":"m u_2 s","agentID":1}],[{"command":"m u_1 c","agentID":0},{"command":"m u_2 c","agentID":1}],[{"command":"m u_1 n","agentID":0},{"command":"m u_2 n","agentID":1}],[],[{"command":"m u_1 s","agentID":0},{"command":"m u_2 s","agentID":1}],[{"command":"m u_1 c","agentID":0},{"command":"m u_2 c","agentID":1}],[{"command":"m u_1 n","agentID":0},{"command":"m u_2 n","agentID":1}],[],[{"command":"m u_1 s","agentID":0},{"command":"m u_2 s","agentID":1}],[{"command":"m u_1 c","agentID":0},{"command":"m u_2 c","agentID":1}],[{"command":"m u_1 n","agentID":0},{"command":"m u_2 n","agentID":1}],[],[{"command":"m u_1 s","agentID":0},{"command":"m u_2 s","agentID":1}],[{"command":"m u_1 c","agentID":0},{"command":"m u_2 c","agentID":1}],[{"command":"m u_1 n","agentID":0},{"command":"m u_2 n","agentID":1}],[],[{"command":"m u_1 s","agentID":0},{"command":"m u_2 s","agentID":1}],[{"command":"m u_1 c","agentID":0},{"command":"m u_2 c","agentID":1}],[{"command":"m u_1 n","agentID":0},{"command":"m u_2 n","agentID":1}],[],[],[],[{"command":"m u_1 s","agentID":0},{"command":"m u_2 s","agentID":1}],[{"command":"m u_1 c","agentID":0},{"command":"m u_2 c","agentID":1}],[{"command":"m u_1 c","agentID":0},{"command":"m u_2 c","agentID":1}],[{"command":"m u_1 c","agentID":0},{"command":"m u_2 c","agentID":1}],[{"command":"m u_1 c","agentID":0},{"command":"m u_2 c","agentID":1}],[{"command":"m u_1 c","agentID":0},{"command":"m u_2 c","agentID":1}],[{"command":"m u_1 c","agentID":0},{"command":"m u_2 c","agentID":1}],[{"command":"m u_1 n","agentID":0},{"command":"m u_2 n","agentID":1}],[],[{"command":"m u_1 s","agentID":0},{"command":"m u_2 s","agentID":1}],[{"command":"m u_1 c","agentID":0},{"command":"m u_2 c","agentID":1}],[{"command":"m u_1 n","agentID":0},{"command":"m u_2 n","agentID":1}],[],[{"command":"m u_1 s","agentID":0},{"command":"m u_2 s","agentID":1}],[{"command":"m u_1 c","agentID":0},{"command":"m u_2 c","agentID":1}],[{"command":"m u_1 n","agentID":0},{"command":"m u_2 n","agentID":1}],[],[{"command":"m u_1 s","agentID":0},{"command":"m u_2 s","agentID":1}],[{"command":"m u_1 c","agentID":0},{"command":"m u_2 c","agentID":1}],[{"command":"m u_1 n","agentID":0},{"command":"m u_2 n","agentID":1}],[],[{"command":"m u_1 s","agentID":0},{"command":"m u_2 s","agentID":1}],[{"command":"m u_1 c","agentID":0},{"command":"m u_2 c","agentID":1}],[{"command":"m u_1 n","agentID":0},{"command":"m u_2 n","agentID":1}],[],[{"command":"m u_1 s","agentID":0},{"command":"m u_2 s","agentID":1}],[{"command":"m u_1 c","agentID":0},{"command":"m u_2 c","agentID":1}],[{"command":"m u_1 n","agentID":0},{"command":"m u_2 n","agentID":1}],[],[{"command":"m u_1 s","agentID":0},{"command":"m u_2 s","agentID":1}],[{"command":"m u_1 w","agentID":0},{"command":"m u_2 w","agentID":1}],[],[{"command":"m u_1 n","agentID":0},{"command":"m u_2 n","agentID":1}],[],[{"command":"bcity u_1","agentID":0},{"command":"bcity u_2","agentID":1}],[{"command":"m u_1 s","agentID":0},{"command":"m u_2 s","agentID":1}],[{"command":"m u_1 c","agentID":0},{"command":"m u_2 c","agentID":1}],[{"command":"m u_1 c","agentID":0},{"command":"m u_2 c","agentID":1}],[{"command":"m u_1 c","agentID":0},{"command":"m u_2 c","agentID":1}],[{"command":"m u_1 c","agentID":0},{"command":"m u_2 c","agentID":1}],[{"command":"m u_1 c","agentID":0},{"command":"m u_2 c","agentID":1}],[{"command":"m u_1 c","agentID":0},{"command":"m u_2 c","agentID":1}],[{"command":"m u_1 c","agentID":0},{"command":"m u_2 c","agentID":1}],[{"command":"m u_1 c","agentID":0},{"command":"m u_2 c","agentID":1}],[{"command":"m u_1 c","agentID":0},{"command":"m u_2 c","agentID":1}],[{"command":"m u_1 c","agentID":0},{"command":"m u_2 c","agentID":1}],[{"command":"m u_1 c","agentID":0},{"command":"m u_2 c","agentID":1}],[{"command":"m u_1 n","agentID":0},{"command":"m u_2 n","agentID":1}],[],[{"command":"m u_1 s","agentID":0},{"command":"m u_2 s","agentID":1}],[{"command":"m u_1 c","agentID":0},{"command":"m u_2 c","agentID":1}],[{"command":"m u_1 c","agentID":0},{"command":"m u_2 c","agentID":1}],[{"command":"m u_1 n","agentID":0},{"command":"m u_2 n","agentID":1}],[],[{"command":"m u_1 s","agentID":0},{"command":"m u_2 s","agentID":1}],[{"command":"m u_1 c","agentID":0},{"command":"m u_2 c","agentID":1}],[{"command":"m u_1 c","agentID":0},{"command":"m u_2 c","agentID":1}],[{"command":"m u_1 n","agentID":0},{"command":"m u_2 n","agentID":1}],[],[{"command":"m u_1 s","agentID":0},{"command":"m u_2 s","agentID":1}],[{"command":"m u_1 c","agentID":0},{"command":"m u_2 c","agentID":1}],[{"command":"m u_1 c","agentID":0},{"command":"m u_2 c","agentID":1}],[{"command":"m u_1 n","agentID":0},{"command":"m u_2 n","agentID":1}],[],[{"command":"m u_1 w","agentID":0},{"command":"m u_2 n","agentID":1}],[{"command":"m u_1 w","agentID":0},{"command":"m u_2 w","agentID":1}],[],[{"command":"m u_1 e","agentID":0},{"command":"m u_2 e","agentID":1}],[],[{"command":"m u_1 e","agentID":0},{"command":"m u_2 s","agentID":1}],[],[{"command":"m u_1 w","agentID":0},{"command":"m u_2 n","agentID":1}],[{"command":"m u_1 w","agentID":0},{"command":"m u_2 w","agentID":1}],[],[{"command":"m u_1 e","agentID":0},{"command":"m u_2 e","agentID":1}],[],[{"command":"bcity u_1","agentID":0},{"command":"bcity u_2","agentID":1}],[{"command":"m u_1 w","agentID":0},{"command":"m u_2 w","agentID":1}],[{"command":"m u_1 c","agentID":0},{"command":"m u_2 c","agentID":1}],[{"command":"m u_1 c","agentID":0},{"command":"m u_2 c","agentID":1}],[{"command":"m u_1 c","agentID":0},{"command":"m u_2 c","agentID":1}],[{"command":"m u_1 c","agentID":0},{"command":"m u_2 c","agentID":1}],[{"command":"m u_1 c","agentID":0},{"command":"m u_2 c","agentID":1}],[{"command":"m u_1 c","agentID":0},{"command":"m u_2 c","agentID":1}],[{"command":"m u_1 c","agentID":0},{"command":"m u_2 c","agentID":1}],[{"command":"m u_1 c","agentID":0},{"command":"m u_2 c","agentID":1}],[{"command":"m u_1 c","agentID":0},{"command":"m u_2 c","agentID":1}],[{"command":"m u_1 e","agentID":0},{"command":"m u_2 e","agentID":1}],[],[{"command":"m u_1 w","agentID":0},{"command":"m u_2 w","agentID":1}],[{"command":"m u_1 c","agentID":0},{"command":"m u_2 c","agentID":1}],[{"command":"m u_1 c","agentID":0},{"command":"m u_2 c","agentID":1}],[{"command":"m u_1 e","agentID":0},{"command":"m u_2 e","agentID":1}],[],[{"command":"m u_1 w","agentID":0},{"command":"m u_2 w","agentID":1}],[{"command":"m u_1 c","agentID":0},{"command":"m u_2 c","agentID":1}],[{"command":"m u_1 c","agentID":0},{"command":"m u_2 c","agentID":1}],[{"command":"m u_1 e","agentID":0},{"command":"m u_2 e","agentID":1}],[],[{"command":"m u_1 w","agentID":0},{"command":"m u_2 w","agentID":1}],[{"command":"m u_1 c","agentID":0},{"command":"m u_2 c","agentID":1}],[{"command":"m u_1 c","agentID":0},{"command":"m u_2 c","agentID":1}],[{"command":"m u_1 e","agentID":0},{"command":"m u_2 e","agentID":1}],[],[{"command":"m u_1 w","agentID":0},{"command":"m u_2 w","agentID":1}],[{"command":"m u_1 c","agentID":0},{"command":"m u_2 c","agentID":1}],[{"command":"m u_1 c","agentID":0},{"command":"m u_2 c","agentID":1}],[{"command":"m u_1 e","agentID":0},{"command":"m u_2 e","agentID":1}],[],[{"command":"m u_1 w","agentID":0},{"command":"m u_2 w","agentID":1}],[{"command":"m u_1 c","agentID":0},{"command":"m u_2 c","agentID":1}],[{"command":"m u_1 c","agentID":0},{"command":"m u_2 c","agentID":1}],[{"command":"m u_1 e","agentID":0},{"command":"m u_2 e","agentID":1}],[],[{"command":"m u_1 w","agentID":0},{"command":"m u_2 w","agentID":1}],[{"command":"m u_1 c","agentID":0},{"command":"m u_2 c","agentID":1}],[{"command":"m u_1 c","agentID":0},{"command":"m u_2 c","agentID":1}],[{"command":"m u_1 c","agentID":0},{"command":"m u_2 c","agentID":1}],[{"command":"m u_1 c","agentID":0},{"command":"m u_2 c","agentID":1}],[{"command":"m u_1 c","agentID":0},{"command":"m u_2 c","agentID":1}],[{"command":"m u_1 c","agentID":0},{"command":"m u_2 c","agentID":1}],[{"command":"m u_1 c","agentID":0},{"command":"m u_2 c","agentID":1}],[{"command":"m u_1 c","agentID":0},{"command":"m u_2 c","agentID":1}],[{"command":"m u_1 c","agentID":0},{"command":"m u_2 c","agentID":1}],[{"command":"m u_1 c","agentID":0},{"command":"m u_2 c","agentID":1}],[{"command":"m u_1 c","agentID":0},{"command":"m u_2 c","agentID":1}],[{"command":"m u_1 c","agentID":0},{"command":"m u_2 c","agentID":1}],[{"command":"m u_1 e","agentID":0},{"command":"m u_2 e","agentID":1}],[],[{"command":"m u_1 w","agentID":0},{"command":"m u_2 w","agentID":1}],[{"command":"m u_1 c","agentID":0},{"command":"m u_2 c","agentID":1}],[{"command":"m u_1 c","agentID":0},{"command":"m u_2 c","agentID":1}],[{"command":"m u_1 e","agentID":0},{"command":"m u_2 e","agentID":1}],[],[{"command":"m u_1 w","agentID":0},{"command":"m u_2 w","agentID":1}],[{"command":"m u_1 c","agentID":0},{"command":"m u_2 c","agentID":1}],[{"command":"m u_1 c","agentID":0},{"command":"m u_2 c","agentID":1}],[{"command":"m u_1 e","agentID":0},{"command":"m u_2 e","agentID":1}],[],[{"command":"m u_1 w","agentID":0},{"command":"m u_2 w","agentID":1}],[{"command":"m u_1 c","agentID":0},{"command":"m u_2 c","agentID":1}],[{"command":"m u_1 c","agentID":0},{"command":"m u_2 c","agentID":1}],[{"command":"m u_1 e","agentID":0},{"command":"m u_2 e","agentID":1}],[],[{"command":"m u_1 w","agentID":0},{"command":"m u_2 w","agentID":1}],[{"command":"m u_1 c","agentID":0},{"command":"m u_2 c","agentID":1}],[{"command":"m u_1 c","agentID":0},{"command":"m u_2 c","agentID":1}],[{"command":"m u_1 e","agentID":0},{"command":"m u_2 e","agentID":1}],[],[{"command":"m u_1 w","agentID":0},{"command":"m u_2 w","agentID":1}],[{"command":"m u_1 c","agentID":0},{"command":"m u_2 c","agentID":1}],[{"command":"m u_1 c","agentID":0},{"command":"m u_2 c","agentID":1}],[{"command":"m u_1 e","agentID":0},{"command":"m u_2 e","agentID":1}],[],[{"command":"m u_1 w","agentID":0},{"command":"m u_2 s","agentID":1}],[{"command":"m u_1 c","agentID":0},{"command":"m u_2 s","agentID":1}],[{"command":"m u_1 c","agentID":0},{"command":"m u_2 w","agentID":1}],[{"command":"m u_1 c","agentID":0}],[{"command":"m u_1 c","agentID":0}],[{"command":"m u_1 c","agentID":0}],[{"command":"m u_1 c","agentID":0},{"command":"m u_2 c","agentID":1}],[{"command":"m u_1 c","agentID":0},{"command":"m u_2 c","agentID":1}],[{"command":"m u_1 c","agentID":0},{"command":"m u_2 c","agentID":1}],[{"command":"m u_1 c","agentID":0},{"command":"m u_2 c","agentID":1}],[{"command":"m u_1 c","agentID":0},{"command":"m u_2 c","agentID":1}],[{"command":"m u_1 c","agentID":0},{"command":"m u_2 c","agentID":1}],[{"command":"m u_1 c","agentID":0},{"command":"m u_2 c","agentID":1}],[{"command":"m u_1 e","agentID":0},{"command":"m u_2 n","agentID":1}],[],[{"command":"m u_1 w","agentID":0},{"command":"m u_2 e","agentID":1}],[{"command":"m u_1 c","agentID":0}],[{"command":"m u_1 c","agentID":0},{"command":"m u_2 s","agentID":1}],[{"command":"m u_1 c","agentID":0},{"command":"m u_2 w","agentID":1}],[{"command":"m u_1 c","agentID":0}],[{"command":"m u_1 e","agentID":0},{"command":"m u_2 n","agentID":1}],[],[{"command":"m u_1 w","agentID":0},{"command":"m u_2 e","agentID":1}],[{"command":"m u_1 e","agentID":0}],[{"command":"m u_2 s","agentID":1}],[{"command":"m u_1 s","agentID":0},{"command":"m u_2 w","agentID":1}],[{"command":"m u_1 c","agentID":0}],[{"command":"m u_1 c","agentID":0},{"command":"m u_2 n","agentID":1}],[{"command":"m u_1 c","agentID":0}],[{"command":"m u_1 c","agentID":0},{"command":"m u_2 e","agentID":1}],[{"command":"m u_1 n","agentID":0}],[{"command":"m u_2 s","agentID":1}],[{"command":"m u_1 s","agentID":0},{"command":"m u_2 w","agentID":1}],[{"command":"m u_1 c","agentID":0}],[{"command":"m u_1 c","agentID":0},{"command":"m u_2 n","agentID":1}],[{"command":"m u_1 c","agentID":0}],[{"command":"m u_1 c","agentID":0},{"command":"m u_2 e","agentID":1}],[{"command":"m u_1 n","agentID":0}],[{"command":"m u_2 s","agentID":1}],[{"command":"m u_1 s","agentID":0},{"command":"m u_2 w","agentID":1}],[{"command":"m u_1 c","agentID":0}],[{"command":"m u_1 c","agentID":0},{"command":"m u_2 n","agentID":1}],[{"command":"m u_1 c","agentID":0}],[{"command":"m u_1 c","agentID":0},{"command":"m u_2 s","agentID":1}],[{"command":"m u_1 c","agentID":0}],[{"command":"m u_1 c","agentID":0}],[{"command":"m u_1 c","agentID":0}],[{"command":"m u_1 c","agentID":0},{"command":"m u_2 c","agentID":1}],[{"command":"m u_1 c","agentID":0},{"command":"m u_2 c","agentID":1}],[{"command":"m u_1 c","agentID":0},{"command":"m u_2 c","agentID":1}],[{"command":"m u_1 c","agentID":0},{"command":"m u_2 c","agentID":1}],[{"command":"m u_1 c","agentID":0},{"command":"m u_2 c","agentID":1}],[{"command":"m u_1 c","agentID":0},{"command":"m u_2 c","agentID":1}],[{"command":"m u_1 n","agentID":0},{"command":"m u_2 n","agentID":1}],[],[{"command":"m u_1 s","agentID":0},{"command":"m u_2 e","agentID":1}],[{"command":"m u_1 c","agentID":0}],[{"command":"m u_1 c","agentID":0},{"command":"m u_2 s","agentID":1}],[{"command":"m u_1 e","agentID":0},{"command":"m u_2 w","agentID":1}],[],[{"command":"m u_1 e","agentID":0},{"command":"m u_2 n","agentID":1}],[],[{"command":"m u_1 e","agentID":0},{"command":"m u_2 e","agentID":1}],[],[{"command":"m u_1 n","agentID":0},{"command":"m u_2 s","agentID":1}],[{"command":"m u_2 w","agentID":1}],[{"command":"m u_1 w","agentID":0}],[{"command":"m u_2 n","agentID":1}],[{"command":"m u_1 e","agentID":0}],[{"command":"m u_1 s","agentID":0},{"command":"m u_2 e","agentID":1}],[],[{"command":"m u_1 n","agentID":0},{"command":"m u_2 s","agentID":1}],[{"command":"m u_2 w","agentID":1}],[{"command":"m u_1 w","agentID":0}],[{"command":"m u_2 n","agentID":1}],[{"command":"m u_1 e","agentID":0}],[{"command":"m u_1 s","agentID":0},{"command":"m u_2 e","agentID":1}],[],[{"command":"m u_1 n","agentID":0},{"command":"m u_2 s","agentID":1}],[{"command":"m u_2 w","agentID":1}],[{"command":"m u_1 w","agentID":0}],[{"command":"m u_2 n","agentID":1}],[{"command":"m u_1 e","agentID":0}],[{"command":"m u_1 s","agentID":0},{"command":"m u_2 s","agentID":1}],[],[],[],[{"command":"m u_1 c","agentID":0},{"command":"m u_2 c","agentID":1}],[{"command":"m u_1 c","agentID":0},{"command":"m u_2 c","agentID":1}],[{"command":"m u_1 c","agentID":0},{"command":"m u_2 c","agentID":1}],[{"command":"m u_1 c","agentID":0},{"command":"m u_2 c","agentID":1}],[{"command":"m u_1 c","agentID":0},{"command":"m u_2 c","agentID":1}],[{"command":"m u_1 c","agentID":0},{"command":"m u_2 c","agentID":1}],[{"command":"m u_1 n","agentID":0},{"command":"m u_2 n","agentID":1}],[],[{"command":"m u_1 w","agentID":0},{"command":"m u_2 e","agentID":1}],[],[{"command":"m u_1 e","agentID":0},{"command":"m u_2 s","agentID":1}],[{"command":"m u_1 s","agentID":0},{"command":"m u_2 w","agentID":1}],[],[{"command":"m u_1 n","agentID":0},{"command":"m u_2 n","agentID":1}],[],[{"command":"m u_1 w","agentID":0},{"command":"m u_2 e","agentID":1}],[],[{"command":"m u_1 e","agentID":0},{"command":"m u_2 s","agentID":1}],[{"command":"m u_1 s","agentID":0},{"command":"m u_2 w","agentID":1}],[],[{"command":"m u_1 n","agentID":0},{"command":"m u_2 n","agentID":1}],[],[{"command":"m u_1 w","agentID":0},{"command":"m u_2 e","agentID":1}],[],[{"command":"m u_1 e","agentID":0},{"command":"m u_2 s","agentID":1}],[{"command":"m u_1 s","agentID":0},{"command":"m u_2 w","agentID":1}],[],[{"command":"m u_1 n","agentID":0},{"command":"m u_2 n","agentID":1}],[],[{"command":"m u_1 w","agentID":0},{"command":"m u_2 e","agentID":1}],[],[{"command":"m u_1 e","agentID":0},{"command":"m u_2 s","agentID":1}],[{"command":"m u_1 s","agentID":0},{"command":"m u_2 w","agentID":1}],[],[{"command":"m u_1 n","agentID":0},{"command":"m u_2 n","agentID":1}],[],[{"command":"m u_1 s","agentID":0},{"command":"m u_2 s","agentID":1}],[],[],[],[{"command":"m u_1 c","agentID":0},{"command":"m u_2 c","agentID":1}],[{"command":"m u_1 c","agentID":0},{"command":"m u_2 c","agentID":1}],[{"command":"m u_1 e","agentID":0},{"command":"m u_2 c","agentID":1}],[{"command":"m u_2 c","agentID":1}],[{"command":"m u_2 c","agentID":1}],[{"command":"m u_2 c","agentID":1}],[{"command":"m u_1 n","agentID":0},{"command":"m u_2 n","agentID":1}],[],[{"command":"m u_1 w","agentID":0},{"command":"m u_2 e","agentID":1}],[],[{"command":"m u_1 w","agentID":0},{"command":"m u_2 s","agentID":1}],[{"command":"m u_2 w","agentID":1}],[{"command":"m u_1 e","agentID":0}],[{"command":"m u_1 e","agentID":0},{"command":"m u_2 n","agentID":1}],[],[{"command":"m u_1 e","agentID":0},{"command":"m u_2 e","agentID":1}],[],[{"command":"m u_1 s","agentID":0},{"command":"m u_2 s","agentID":1}],[{"command":"m u_2 w","agentID":1}],[{"command":"m u_1 n","agentID":0},{"command":"m u_2 w","agentID":1}],[],[{"command":"m u_1 w","agentID":0},{"command":"m u_2 n","agentID":1}],[],[{"command":"m u_1 w","agentID":0},{"command":"m u_2 e","agentID":1}],[],[{"command":"m u_1 w","agentID":0},{"command":"m u_2 s","agentID":1}],[{"command":"m u_2 w","agentID":1}],[{"command":"m u_1 e","agentID":0}],[{"command":"m u_1 e","agentID":0},{"command":"m u_2 s","agentID":1}],[],[{"command":"m u_1 s","agentID":0},{"command":"m u_2 n","agentID":1}],[],[{"command":"m u_1 s","agentID":0},{"command":"m u_2 n","agentID":1}],[],[{"command":"m u_1 n","agentID":0},{"command":"m u_2 e","agentID":1}],[],[{"command":"m u_1 s","agentID":0},{"command":"m u_2 e","agentID":1}],[{"command":"m u_2 e","agentID":1}],[{"command":"m u_2 s","agentID":1}],[],[{"command":"m u_1 c","agentID":0}],[{"command":"m u_1 c","agentID":0}],[{"command":"m u_1 c","agentID":0},{"command":"m u_2 c","agentID":1}],[{"command":"m u_1 c","agentID":0},{"command":"m u_2 c","agentID":1}],[{"command":"m u_1 c","agentID":0},{"command":"m u_2 c","agentID":1}]],"mapType":"random","teamDetails":[{"name":"main.py","tournamentID":""},{"name":"main.py","tournamentID":""}],"version":"1.2.1","results":{"ranks":[{"rank":1,"agentID":0},{"rank":2,"agentID":1}],"replayFile":"replays/1626110360573_r3MWD1WItvZn.json"}}